edustudio/__init__.py
edustudio/settings.py
edustudio/assets/datasets.yaml
edustudio/atom_op/__init__.py
edustudio/atom_op/mid2cache/__init__.py
edustudio/atom_op/mid2cache/CD/__init__.py
edustudio/atom_op/mid2cache/CD/data_split4cd.py
edustudio/atom_op/mid2cache/CD/filter_records4cd.py
edustudio/atom_op/mid2cache/KT/__init__.py
edustudio/atom_op/mid2cache/KT/build_seq_inter_feats.py
edustudio/atom_op/mid2cache/KT/cpt_as_exer.py
edustudio/atom_op/mid2cache/KT/data_split4kt.py
edustudio/atom_op/mid2cache/KT/gen_cpt_seq.py
edustudio/atom_op/mid2cache/KT/gen_unfold_cpt_seq.py
edustudio/atom_op/mid2cache/common/__init__.py
edustudio/atom_op/mid2cache/common/base_mid2cache.py
edustudio/atom_op/mid2cache/common/build_cpt_relation.py
edustudio/atom_op/mid2cache/common/build_missing_Q.py
edustudio/atom_op/mid2cache/common/fill_missing_Q.py
edustudio/atom_op/mid2cache/common/filtering_records_by_attr.py
edustudio/atom_op/mid2cache/common/gen_q_mat.py
edustudio/atom_op/mid2cache/common/label2int.py
edustudio/atom_op/mid2cache/common/merge_divided_splits.py
edustudio/atom_op/mid2cache/common/remapid.py
edustudio/atom_op/mid2cache/single/M2C_CDGK_OP.py
edustudio/atom_op/mid2cache/single/M2C_CL4KT_OP.py
edustudio/atom_op/mid2cache/single/M2C_CNCDQ_OP.py
edustudio/atom_op/mid2cache/single/M2C_DIMKT_OP.py
edustudio/atom_op/mid2cache/single/M2C_DKTDSC_OP.py
edustudio/atom_op/mid2cache/single/M2C_DKTForget_OP.py
edustudio/atom_op/mid2cache/single/M2C_EERNN_OP.py
edustudio/atom_op/mid2cache/single/M2C_LPKT_OP.py
edustudio/atom_op/mid2cache/single/M2C_MGCD_OP.py
edustudio/atom_op/mid2cache/single/M2C_QDKT_OP.py
edustudio/atom_op/mid2cache/single/M2C_RCD_OP.py
edustudio/atom_op/mid2cache/single/__init__.py
edustudio/atom_op/raw2mid/__init__.py
edustudio/atom_op/raw2mid/aaai_2023.py
edustudio/atom_op/raw2mid/algebra2005.py
edustudio/atom_op/raw2mid/assist_0910.py
edustudio/atom_op/raw2mid/assist_1213.py
edustudio/atom_op/raw2mid/assist_1516.py
edustudio/atom_op/raw2mid/assist_2017.py
edustudio-1.1.7.dist-info/licenses/LICENSE
edustudio-1.1.7.dist-info/METADATA
edustudio-1.1.7.dist-info/WHEEL
edustudio-1.1.7.dist-info/entry_points.txt
edustudio-1.1.7.dist-info/top_level.txt
edustudio-1.1.7.dist-info/RECORD
